ecopackage/func.py
ecopackage-0.1.dist-info/METADATA
ecopackage-0.1.dist-info/WHEEL
ecopackage-0.1.dist-info/top_level.txt
ecopackage-0.1.dist-info/RECORD
