Metadata-Version: 2.1
Name: ecopackage
Version: 0.1
Summary: Functions that will save your life, except when they raise an error.
Home-page: UNKNOWN
Author: UNKNOWN
Author-email: UNKNOWN
License: MIT
Platform: UNKNOWN
